Metadata-Version: 1.1
Name: helga-users
Version: 0.0.2
Summary: Users plugin for Helga
Home-page: https://github.com/ktdreyer/helga-users
Author: ken dreyer
Author-email: ktdreyer@ktdreyer.com
License: MIT
Keywords: irc bot users
Platform: UNKNOWN
Classifier: Development Status :: 4 - Beta
Classifier: License :: OSI Approved :: MIT License
Classifier: Intended Audience :: Developers
Classifier: Operating System :: POSIX
Classifier: Programming Language :: Python
Classifier: Topic :: Software Development
